nlp_date_parser/__init__.py
nlp_date_parser/parser.py
nlp_date_parser-0.0.1.dist-info/licenses/LICENSE
nlp_date_parser-0.0.1.dist-info/METADATA
nlp_date_parser-0.0.1.dist-info/WHEEL
nlp_date_parser-0.0.1.dist-info/top_level.txt
nlp_date_parser-0.0.1.dist-info/RECORD
