Metadata-Version: 2.4
Name: nlp_date_parser
Version: 0.0.1
Summary: A simple NLP-based date parser to extract dates from text.
Home-page: https://github.com/viv1ag/nlp_date_parser
Author: Vivek Agarwal
Author-email: ec.vivek@gmail.com
Classifier: Programming Language :: Python :: 3
Classifier: License :: OSI Approved :: MIT License
Classifier: Operating System :: OS Independent
Requires-Python: >=3.6
License-File: LICENSE
Requires-Dist: parse
Requires-Dist: dateparser
Requires-Dist: spacy
Dynamic: author
Dynamic: author-email
Dynamic: classifier
Dynamic: description
Dynamic: description-content-type
Dynamic: home-page
Dynamic: license-file
Dynamic: requires-dist
Dynamic: requires-python
Dynamic: summary
